my3dengine/UI.py
my3dengine/__init__.py
my3dengine/camera.py
my3dengine/core.py
my3dengine/key.py
my3dengine/mesh.py
my3dengine/sdl2.dll
my3dengine/shader.py
my3dengine/water.py
my3dengine-0.6.0.dist-info/licenses/LICENSE
my3dengine-0.6.0.dist-info/METADATA
my3dengine-0.6.0.dist-info/WHEEL
my3dengine-0.6.0.dist-info/top_level.txt
my3dengine-0.6.0.dist-info/RECORD
